sr_vulkan/__init__.py
sr_vulkan/enum.py
sr_vulkan/hook-sr_vulkan.py
sr_vulkan/sr_vulkan.pyd
sr_vulkan/sr_vulkan.pyi
sr_vulkan-2.0.1.1.dist-info/LICENSE
sr_vulkan-2.0.1.1.dist-info/METADATA
sr_vulkan-2.0.1.1.dist-info/WHEEL
sr_vulkan-2.0.1.1.dist-info/entry_points.txt
sr_vulkan-2.0.1.1.dist-info/top_level.txt
sr_vulkan-2.0.1.1.dist-info/RECORD
