Metadata-Version: 2.1
Name: sr-vulkan
Version: 2.0.1.1
Summary: A super resolution python tool, use nihui/waifu2x-ncnn-vulkan, nihui/realsr-ncnn-vulkan, nihui/realcugan-ncnn-vulkan, xinntao/Real-ESRGAN-ncnn-vulkan
Home-page: https://github.com/tonquer/waifu2x-vulkan
Author: tonquer
Author-email: tonquer@qq.com
License: MIT
Platform: UNKNOWN
Classifier: Operating System :: OS Independent
Classifier: Programming Language :: Python :: 3
Classifier: Programming Language :: Python :: 3.6
Classifier: Programming Language :: Python :: 3.7
Classifier: Programming Language :: Python :: 3.8
Classifier: Programming Language :: Python :: 3.9
Classifier: Programming Language :: Python :: 3.10
Classifier: Programming Language :: Python :: 3.11
Classifier: Programming Language :: Python :: 3.12
Classifier: License :: OSI Approved :: MIT License
Requires-Python: >=3.6
License-File: LICENSE
